scraper_factory/__init__.py
scraper_factory/core/__init__.py
scraper_factory/core/api.py
scraper_factory/core/base_spider.py
scraper_factory/core/exceptions.py
scraper_factory/core/spidermanager.py
scraper_factory/core/utils.py
scraper_factory/core/scraper/__init__.py
scraper_factory/core/scraper/scrapy.py
scraper_factory/spiders/__init__.py
scraper_factory/spiders/amazonwishlist.py
tests/sample_spiders/__init__.py
tests/utils/__init__.py
tests/utils/read_from_file.py
tests/utils/spidertestbase.py
scraper_factory-0.2.1.dist-info/LICENSE
scraper_factory-0.2.1.dist-info/METADATA
scraper_factory-0.2.1.dist-info/WHEEL
scraper_factory-0.2.1.dist-info/top_level.txt
scraper_factory-0.2.1.dist-info/RECORD
