Metadata-Version: 2.1
Name: scraper-factory
Version: 0.2.1
Summary: Scraping library to retrieve data from useful pages, such as Amazon wishlists
Home-page: https://github.com/machinia/scraper-factory
Author: Pablo Ahumada, Jorge Capona
Author-email: pablo.ahumadadiaz@gmail.com, jcapona@gmail.com
License: MIT
Keywords: scraping wishlist amazon
Platform: UNKNOWN
Classifier: Development Status :: 3 - Alpha
Classifier: Intended Audience :: Developers
Classifier: Topic :: Software Development
Classifier: Topic :: System
Classifier: License :: OSI Approved :: MIT License
Classifier: Programming Language :: Python :: 3.6
Requires-Dist: asn1crypto (==0.24.0)
Requires-Dist: attrs (==19.1.0)
Requires-Dist: Automat (==0.7.0)
Requires-Dist: cffi (==1.12.3)
Requires-Dist: constantly (==15.1.0)
Requires-Dist: cryptography (==2.7)
Requires-Dist: cssselect (==1.0.3)
Requires-Dist: hyperlink (==19.0.0)
Requires-Dist: idna (==2.8)
Requires-Dist: incremental (==17.5.0)
Requires-Dist: lxml (==4.4.0)
Requires-Dist: parsel (==1.5.1)
Requires-Dist: pyasn1 (==0.4.5)
Requires-Dist: pyasn1-modules (==0.2.5)
Requires-Dist: pycparser (==2.19)
Requires-Dist: PyDispatcher (==2.0.5)
Requires-Dist: PyHamcrest (==1.9.0)
Requires-Dist: pyOpenSSL (==19.0.0)
Requires-Dist: queuelib (==1.5.0)
Requires-Dist: Scrapy (==1.7.2)
Requires-Dist: service-identity (==18.1.0)
Requires-Dist: six (==1.12.0)
Requires-Dist: Twisted (==19.2.1)
Requires-Dist: w3lib (==1.20.0)
Requires-Dist: zope.interface (==4.6.0)
